<?xml version="1.0" encoding="UTF-8"?>
<outfit name="Ka'Ralt Secession - Main Routes">
 <general>
  <mass>0</mass>
  <price>1000</price>
  <description>Main trade routes between Ka'Ralt Secession worlds</description>
  <gfx_store>map</gfx_store>
 </general>
 <specific type="map">
  <sys name="Ka'Ralt Corridor">
   <jump>KR 0001</jump>
   <jump>Ka'Ralt Crossing</jump>
  </sys>
  <sys name="Nat'Erka">
   <jump>KR 0016</jump>
   <jump>KR 0023</jump>
   <asset>Nat'Erka</asset>
  </sys>
  <sys name="K'Tilk'Elh">
   <jump>KR 0038</jump>
   <asset>K'Tilk'Elh</asset>
  </sys>
  <sys name="KR 0002">
   <jump>KR 0015</jump>
   <jump>Ka'Ralt</jump>
  </sys>
  <sys name="KR 0015">
   <jump>KR 0002</jump>
   <jump>KR 0016</jump>
   <jump>KR 0017</jump>
  </sys>
  <sys name="KR 0016">
   <jump>KR 0015</jump>
   <jump>Nat'Erka</jump>
  </sys>
  <sys name="KR 0001">
   <jump>Ka'Ralt</jump>
   <jump>Ka'Ralt Corridor</jump>
  </sys>
  <sys name="KR 0013">
   <jump>KR 0012</jump>
  </sys>
  <sys name="KR 0012">
   <jump>KR 0011</jump>
   <jump>KR 0013</jump>
  </sys>
  <sys name="KR 0011">
   <jump>KR 0006</jump>
   <jump>KR 0012</jump>
  </sys>
  <sys name="KR 0006">
   <jump>KR 0007</jump>
   <jump>KR 0011</jump>
   <jump>Ka'Ralt</jump>
  </sys>
  <sys name="KR 0017">
   <jump>KR 0015</jump>
   <jump>T'Kell's Reaches</jump>
  </sys>
  <sys name="KR 0020">
   <jump>KR 0019</jump>
   <jump>KR 0021</jump>
   <jump>T'Kell's Reaches</jump>
  </sys>
  <sys name="KR 0021">
   <jump>KR 0020</jump>
   <jump>KR 0038</jump>
  </sys>
  <sys name="KR 0038">
   <jump>K'Tilk'Elh</jump>
   <jump>KR 0021</jump>
   <jump>T'Kell's Fringe</jump>
  </sys>
  <sys name="KR 0034">
   <jump>KR 0035</jump>
  </sys>
  <sys name="KR 0035">
   <jump>KR 0029</jump>
   <jump>KR 0034</jump>
  </sys>
  <sys name="KR 0029">
   <jump>KR 0026</jump>
   <jump>KR 0035</jump>
  </sys>
  <sys name="KR 0026">
   <jump>KR 0025</jump>
   <jump>KR 0029</jump>
  </sys>
  <sys name="KR 0025">
   <jump>KR 0024</jump>
   <jump>KR 0026</jump>
  </sys>
  <sys name="KR 0024">
   <jump>KR 0023</jump>
   <jump>KR 0025</jump>
  </sys>
  <sys name="KR 0023">
   <jump>KR 0024</jump>
   <jump>Nat'Erka</jump>
  </sys>
  <sys name="KR 0049">
   <jump>KR 0008</jump>
   <jump>KR 0009</jump>
  </sys>
  <sys name="KR 0009">
   <jump>KR 0007</jump>
   <jump>KR 0008</jump>
   <jump>KR 0014</jump>
   <jump>KR 0049</jump>
  </sys>
  <sys name="KR 0007">
   <jump>KR 0006</jump>
   <jump>KR 0008</jump>
   <jump>KR 0009</jump>
  </sys>
  <sys name="KR 0014">
   <jump>KR 0009</jump>
   <jump>KR 0019</jump>
  </sys>
  <sys name="KR 0019">
   <jump>KR 0014</jump>
   <jump>KR 0020</jump>
   <jump>T'Kell's Reaches</jump>
  </sys>
  <sys name="KR 0041">
   <jump>KR 0042</jump>
   <jump>T'Kell's Fringe</jump>
  </sys>
  <sys name="KR 0042">
   <jump>KR 0041</jump>
  </sys>
  <sys name="KR 0008">
   <jump>KR 0007</jump>
   <jump>KR 0009</jump>
   <jump>KR 0040</jump>
   <jump>KR 0049</jump>
  </sys>
  <sys name="KR 0040">
   <jump>KR 0008</jump>
  </sys>
  <sys name="Ka'Ralt Crossing">
   <jump>Ka'Ralt Corridor</jump>
   <asset>K'Tint</asset>
   <asset>K'Tint Nilal</asset>
  </sys>
  <sys name="Ka'Ralt">
   <jump>KR 0001</jump>
   <jump>KR 0002</jump>
   <jump>KR 0006</jump>
   <asset>Ka'Ralt</asset>
   <asset>Ren'Lin</asset>
  </sys>
  <sys name="T'Kell's Reaches">
   <jump>KR 0017</jump>
   <jump>KR 0019</jump>
   <jump>KR 0020</jump>
   <asset>T'Kell Outpost</asset>
  </sys>
  <sys name="T'Kell's Fringe">
   <jump>KR 0038</jump>
   <jump>KR 0041</jump>
   <jump>T'Kell's Shortcut</jump>
   <asset>T'Kell</asset>
  </sys>
  <sys name="T'Kell's Shortcut">
   <jump>T'Kell's Fringe</jump>
  </sys>
 </specific>
</outfit>
